{
    "0": "Queen",
    "1": "Quavo",
    "2": "Quin Nfn",
    "3": "Qumu",
    "4": "Quinn Lewis",
    "5": "Qveen Herby",
    "6": "Queen Latifah",
    "7": "Q Money",
    "8": "QoryGore",
    "9": "Quang Linh",
    "10": "Quadron",
    "11": "Quang Le",
    "12": "Quang Ha",
    "13": "Nhu Quynh",
    "14": "Manh Quynh",
    "16": "Quoc Khanh",
    "17": "Quynh Trang",
    "19": "Queen Key",
    "20": "Phan Manh Quynh",
    "21": "Ho Quynh Huong",
    "22": "Queens Of The Stone Age",
    "23": "Trinh Dinh Quang",
    "24": "Quentin Miller",
    "25": "Ho Quang Hieu",
    "26": "Quicksand",
    "27": "Quicksilver Messenger Service",
    "28": "Quietdrive",
    "29": "Quiet Riot",
    "30": "Quiles, Justin",
    "31": "Quincy",
    "32": "Quincy Jones",
    "33": "Quinlan, Frances",
    "34": "Quin NFN",
    "35": "Quinn XCII",
    "36": "Quintana, Pepe",
    "37": "Quinto, Angeline",
    "38": "Quiroz, Patrick",
    "39": "Quiwa, Patch",
    "41": "Qwote"
}